[
  {
    "reference": "树绕村庄，水满陂塘。倚东风、豪兴徜徉。",
    "student_response": "绿树环绕着村庄，春水溢满池塘，沐浴着东风，带着豪兴我信步而行。",
    "score": 93
  },
  {
    "reference": "小园几许，收尽春光。有桃花红，李花白，菜花黄。",
    "student_response": "小园虽小，却收尽了春光。桃花正红，李花雪白，菜花金黄。",
    "score": 96
  },
  {
    "reference": "远远围墙，隐隐茅堂。飏青旗、流水桥旁。",
    "student_response": "远远一带围墙，隐约有几间茅草屋。青色的旗帜在风中飞扬，小桥矗立在溪水旁。",
    "score": 90
  },
  {
    "reference": "偶然乘兴、步过东冈。正莺儿啼，燕儿舞，蝶儿忙。",
    "student_response": "偶然乘着游兴，走过东面的山冈。莺儿鸣啼，燕儿飞舞，蝶儿匆忙。",
    "score": 88
  }
] 